fastaccess/_backend.py
fastaccess/store.py
fastaccess/_fastaccess_cpp.cpython-39-x86_64-linux-gnu.so
fastaccess/_fastaccess_cpp.pyi
fastaccess/py.typed
fastaccess/api.py
fastaccess/__init__.py
fastaccess/index.py
fastaccess/tests/test_gzip.py
fastaccess/tests/test_cpp_bindings.py
fastaccess/tests/__init__.py
fastaccess/tests/test_fastaccess.py
fastaccess-0.2.1.dist-info/WHEEL
fastaccess-0.2.1.dist-info/METADATA
fastaccess-0.2.1.dist-info/RECORD
